syphonpy.cpython-38-darwin.so
syphonpy-0.0.2.dist-info/METADATA
syphonpy-0.0.2.dist-info/WHEEL
syphonpy-0.0.2.dist-info/top_level.txt
syphonpy-0.0.2.dist-info/RECORD
