Metadata-Version: 2.1
Name: syphonpy
Version: 0.0.2
Summary: Python bindings for the Syphon Framework (OSX).
Home-page: UNKNOWN
License: UNKNOWN
Platform: UNKNOWN
